xontrib/zsh_cd_dot.py
xontrib_zsh_cd_dot-0.1.1.dist-info/WHEEL
xontrib_zsh_cd_dot-0.1.1.dist-info/METADATA
xontrib_zsh_cd_dot-0.1.1.dist-info/RECORD
